pycallingcards/__init__.py
pycallingcards/datasets/__init__.py
pycallingcards/datasets/_datasets.py
pycallingcards/plotting/_Chipseq.py
pycallingcards/plotting/_GWAS.py
pycallingcards/plotting/_WashU_browser.py
pycallingcards/plotting/__init__.py
pycallingcards/plotting/_dotplots.py
pycallingcards/plotting/_heatmap_ccrna.py
pycallingcards/plotting/_pair.py
pycallingcards/plotting/_peaks.py
pycallingcards/plotting/_plotting.py
pycallingcards/plotting/_volcano.py
pycallingcards/preprocessing/__init__.py
pycallingcards/preprocessing/_annotation.py
pycallingcards/preprocessing/_blo_algorithms.py
pycallingcards/preprocessing/_blo_segmentation.py
pycallingcards/preprocessing/_blo_utilities.py
pycallingcards/preprocessing/_callpeaks.py
pycallingcards/preprocessing/_clean.py
pycallingcards/preprocessing/_filterpeaks.py
pycallingcards/preprocessing/_makeadata.py
pycallingcards/reading/__init__.py
pycallingcards/reading/_read.py
pycallingcards/tools/_GWAS.py
pycallingcards/tools/__init__.py
pycallingcards/tools/_call_motif.py
pycallingcards/tools/_find_fastq.py
pycallingcards/tools/_find_related_genes.py
pycallingcards/tools/_footprint.py
pycallingcards/tools/_liftover.py
pycallingcards/tools/_rank_peaks_group.py
pycallingcards-1.0.0.dist-info/LICENSE
pycallingcards-1.0.0.dist-info/METADATA
pycallingcards-1.0.0.dist-info/WHEEL
pycallingcards-1.0.0.dist-info/top_level.txt
pycallingcards-1.0.0.dist-info/RECORD
