Metadata-Version: 2.1
Name: pycallingcards
Version: 1.0.0
Summary: "Calling cards data analysis in Python."
Home-page: https://github.com/The-Mitra-Lab/pycallingcards
Author: "The-Mitra-Lab"
Author-email: "rmitra@wustl.edu"
License: BSD 3-Clause License
Platform: any
Requires-Python: >=3.8
License-File: LICENSE
Requires-Dist: numpy >=1.22.3
Requires-Dist: pandas >=1.4.3
Requires-Dist: tqdm >=4.63.0
Requires-Dist: scipy >=1.8.1
Requires-Dist: anndata >=0.8.0
Requires-Dist: numba >=0.55.2
Requires-Dist: matplotlib >=3.5.2
Requires-Dist: scanpy >=1.9.1
Requires-Dist: seaborn >=0.12.1
Requires-Dist: pybedtools >=0.9.0
Requires-Dist: appdirs >=1.4.4
Requires-Dist: pyBigWig >=0.3.18
Requires-Dist: mudata >=0.2.1
Requires-Dist: requests ==2.28.2
Requires-Dist: statsmodels >=0.13.5
Requires-Dist: liftover
